suno_py/__init__.py
suno_py/_base_client.py
suno_py/_version.py
suno_py/api.py
suno_py/exception.py
suno_py/requests.py
suno_py/responses.py
suno_py/suno.py
suno_py/utils.py
suno_py/version.py
suno_py-0.1.0.dist-info/METADATA
suno_py-0.1.0.dist-info/WHEEL
suno_py-0.1.0.dist-info/RECORD
