Metadata-Version: 2.3
Name: suno-py
Version: 0.1.0
Summary: Unofficial Python library for the Suno API
Author-email: ldsxp <85176878@qq.com>
Requires-Python: >=3.8
Requires-Dist: loguru>=0.7.2
Requires-Dist: pydantic>=2.6.4
Requires-Dist: requests>=2.31.0
